{
  "parent": "minecraft:recipes/root",
  "rewards": {
    "recipes": [
      "minecraft:bejeweled_galvite_brick_slab_from_bejeweled_galvite_stonecutting"
    ]
  },
  "criteria": {
    "has_bejeweled_galvite": {
      "trigger": "minecraft:inventory_changed",
      "conditions": {
        "items": [
          {
            "item": "mythscapes:bejeweled_galvite"
          }
        ]
      }
    },
    "has_the_recipe": {
      "trigger": "minecraft:recipe_unlocked",
      "conditions": {
        "recipe": "minecraft:bejeweled_galvite_brick_slab_from_bejeweled_galvite_stonecutting"
      }
    }
  },
  "requirements": [
    [
      "has_bejeweled_galvite",
      "has_the_recipe"
    ]
  ]
}